Workbook

Sheet Read me
B2: Vendii feature inventory: trading app and share-backed lending app
B3: Prepared 7 Oct 2026 for Damilola's approval. Font: Space Grotesk.
B5: How to use this
B6: 1 | C6: Go to 'Trading app' and 'Lending app'. Each row is one feature, with what it does, who does it well globally or locally, and how it changes for Nigeria.
B7: 2 | C7: Fill the yellow 'Your call' column with Approve, Reject, Later or Discuss (dropdown). Add anything in 'Your notes'.
B8: 3 | C8: Example: on Trading app row T001 pick 'Approve' and note 'Use Smile ID or Dojah, not in-house'.
B9: 4 | C9: The 'Summary' tab counts features by tier and counts your approvals automatically.
B10: 5 | C10: Tier and release are my recommendation. Release dates follow your roadmap: brokerage Nov 2026 / Feb 2027 / Mar 2027; lending Mar 2027 / May 2027 / Jul 2027.
B12: Tier definitions
B13: Critical | C13: Can't launch, can't keep the licence, or users lose money without it.
B14: Difference maker | C14: The reason someone picks Vendii over Bamboo, Meritrade or VBank. Not table stakes.
B15: Good | C15: Real value for users. Build soon after launch.
B16: Nice to have | C16: Polish or a niche need. Build once the core works.
B17: Not important | C17: Wrong fit for Nigeria or for Vendii's licences right now.
B18: Nah, just there | C18: Competitors have it. It looks good and changes nothing.
B20: Nigerian context that shaped the tiers (sourced; see Sources tab)
B21: Licence cost | C21: SEC raised digital sub-broker minimum capital to ₦100m on 16 Jan 2026. Brokers need ₦600m and broker-dealers ₦2bn. [S4]
B22: Sub-broker duties | C22: Rule 76 requires digital sub-brokers to have technology risk policies, security certifications and client suitability notifications. [S5]
B23: Retail bonds | C23: FGN Savings Bond: ₦5,000 minimum, ₦50m maximum, monthly windows, quarterly coupons. September 2026 rates were 14.12% (2 years) and 15.12% (3 years). [S6]
B24: T-bills and FGN bonds | C24: Primary auctions need over ₦50m per subscription, so retail access runs through funds or partner dealers. [S7]
B25: CSCS liens | C25: CSCS is set to halve retail lien fees and scrap charges on transfers between immediate family (reported 26 Aug 2026; check whether it has taken effect). [S8]
B26: Margin rules | C26: 2010 rules: 120% maintenance margin, bank shares barred from margin trading, bank margin exposure capped at 10% of total loans. [S9] Bank shares can still back ordinary bank loans. [S10]
B27: Local competitor | C27: VBank x Anchoria share-backed overdraft: up to ₦60m (individuals) or ₦300m (corporates), up to six months, 140% margin call and stop-loss trigger, Anchoria clients holding Tier 1 NGX shares only. [S11]
B28: Global lending model | C28: Schwab's Pledged Asset Line is non-purpose: proceeds can't buy securities, and Schwab may sell pledged assets without contacting the client. [S13] Volt Money in India embeds loans in other platforms through SDKs and reverses the lien on repayment. [S14]
B29: App market | C29: Bamboo passed 1M+ Play Store downloads; Meritrade (Meristem) offers NGX and NASD OTC access. [S1] Investors keep several apps because of reliability concerns. [S3]
B31: Not verified (confirm before building)
B32: 1 | C32: Current NGX equity settlement cycle, trading hours and daily price limits.
B33: 2 | C33: Whether CSCS can place a lien in favour of a lender on shares held under any broker, and the steps involved.
B34: 3 | C34: Status of the SEC/CBN revision of margin lending rules.
B35: 4 | C35: Nigerian consumer credit disclosure rules (CBN, FCCPC) and any cooling-off requirement.
B36: 5 | C36: Tax treatment of share disposal gains under the 2025 tax reforms.
B38: My headline calls
B39: 1 | C39: Trading app: the wedge is not more assets than Bamboo. It's the stuff only Vendii can do: import forgotten holdings, recover unclaimed dividends, dividend tracking net of WHT, beneficiary nomination, and honest order status.
B40: 2 | C40: Lending app: lending against shares held at any broker is the whole bet. VBank only lends to Anchoria clients. Confirm the CSCS lien mechanics first; if that fails, the product shrinks to Vendii-held shares only.
B41: 3 | C41: Keep the lending app non-purpose (loans not for buying shares). Margin trading needs a broker-dealer with ₦2bn capital, so it stays in Backlog.
B42: 4 | C42: Skip US stocks, crypto, social feeds and options for now. They're crowded, off-licence or both.

Sheet Summary
B2: Feature count by tier
B4: Tier | C4: Trading app | D4: Lending app | E4: Total
B5: Critical | C5: =COUNTIF('Trading app'!$G$2:$G$120,B5) -> 33 | D5: =COUNTIF('Lending app'!$G$2:$G$67,B5) -> 30 | E5: =C5+D5 -> 63
B6: Difference maker | C6: =COUNTIF('Trading app'!$G$2:$G$120,B6) -> 15 | D6: =COUNTIF('Lending app'!$G$2:$G$67,B6) -> 10 | E6: =C6+D6 -> 25
B7: Good | C7: =COUNTIF('Trading app'!$G$2:$G$120,B7) -> 42 | D7: =COUNTIF('Lending app'!$G$2:$G$67,B7) -> 15 | E7: =C7+D7 -> 57
B8: Nice to have | C8: =COUNTIF('Trading app'!$G$2:$G$120,B8) -> 15 | D8: =COUNTIF('Lending app'!$G$2:$G$67,B8) -> 6 | E8: =C8+D8 -> 21
B9: Not important | C9: =COUNTIF('Trading app'!$G$2:$G$120,B9) -> 8 | D9: =COUNTIF('Lending app'!$G$2:$G$67,B9) -> 3 | E9: =C9+D9 -> 11
B10: Nah, just there | C10: =COUNTIF('Trading app'!$G$2:$G$120,B10) -> 6 | D10: =COUNTIF('Lending app'!$G$2:$G$67,B10) -> 2 | E10: =C10+D10 -> 8
B11: Total | C11: =SUM(C5:C10) -> 119 | D11: =SUM(D5:D10) -> 66 | E11: =SUM(E5:E10) -> 185
B14: Your decisions so far
B16: Your call | C16: Trading app | D16: Lending app | E16: Total
B17: Approve | C17: =COUNTIF('Trading app'!$I$2:$I$120,B17) -> 98 | D17: =COUNTIF('Lending app'!$I$2:$I$67,B17) -> 56 | E17: =C17+D17 -> 154
B18: Reject | C18: =COUNTIF('Trading app'!$I$2:$I$120,B18) -> 0 | D18: =COUNTIF('Lending app'!$I$2:$I$67,B18) -> 0 | E18: =C18+D18 -> 0
B19: Later | C19: =COUNTIF('Trading app'!$I$2:$I$120,B19) -> 21 | D19: =COUNTIF('Lending app'!$I$2:$I$67,B19) -> 10 | E19: =C19+D19 -> 31
B20: Discuss | C20: =COUNTIF('Trading app'!$I$2:$I$120,B20) -> 0 | D20: =COUNTIF('Lending app'!$I$2:$I$67,B20) -> 0 | E20: =C20+D20 -> 0
B21: Not yet decided | C21: =COUNTA('Trading app'!$A$2:$A$120)-SUM(C17:C20) -> 0 | D21: =COUNTA('Lending app'!$A$2:$A$67)-SUM(D17:D20) -> 0 | E21: =C21+D21 -> 0
B24: Approved features by suggested release
B26: Release | C26: Trading app | D26: Release | E26: Lending app
B27: Launch (Nov 2026) | C27: =COUNTIFS('Trading app'!$H$2:$H$120,B27,'Trading app'!$I$2:$I$120,"Approve") -> 52 | D27: Launch (Mar 2027) | E27: =COUNTIFS('Lending app'!$H$2:$H$67,D27,'Lending app'!$I$2:$I$67,"Approve") -> 39
B28: Phase 2 (Feb 2027) | C28: =COUNTIFS('Trading app'!$H$2:$H$120,B28,'Trading app'!$I$2:$I$120,"Approve") -> 27 | D28: Phase 2 (May 2027) | E28: =COUNTIFS('Lending app'!$H$2:$H$67,D28,'Lending app'!$I$2:$I$67,"Approve") -> 11
B29: Phase 3 (Mar 2027) | C29: =COUNTIFS('Trading app'!$H$2:$H$120,B29,'Trading app'!$I$2:$I$120,"Approve") -> 16 | D29: Phase 3 (Jul 2027) | E29: =COUNTIFS('Lending app'!$H$2:$H$67,D29,'Lending app'!$I$2:$I$67,"Approve") -> 4
B30: Backlog | C30: =COUNTIFS('Trading app'!$H$2:$H$120,B30,'Trading app'!$I$2:$I$120,"Approve") -> 3 | D30: Backlog | E30: =COUNTIFS('Lending app'!$H$2:$H$67,D30,'Lending app'!$I$2:$I$67,"Approve") -> 2
B31: Skip | C31: =COUNTIFS('Trading app'!$H$2:$H$120,B31,'Trading app'!$I$2:$I$120,"Approve") -> 0 | D31: Skip | E31: =COUNTIFS('Lending app'!$H$2:$H$67,D31,'Lending app'!$I$2:$I$67,"Approve") -> 0

Sheet Trading app
A1: ID | B1: Module | C1: Feature | D1: What it does | E1: Who does it well | F1: Nigeria adaptation | G1: Tier | H1: Suggested release | I1: Your call | J1: Your notes
A2: T001 | B2: Onboarding & KYC | C2: BVN + NIN check with selfie liveness | D2: Verifies identity in a few minutes from BVN/NIN lookup and a selfie match. | E2: Robinhood, Bamboo, Risevest | F2: Name on BVN must match the bank account and the CSCS record, or trades and dividends break later. Check all three at signup. | G2: Critical | H2: Launch (Nov 2026) | I2: Approve
A3: T002 | B3: Onboarding & KYC | C3: Automatic CSCS account (CHN) opening | D3: Opens the investor's clearing house number through the sponsoring broker with no paper forms. | E3: Meritrade (Meristem), Chaka | F3: Runs through Trust Bank Securities as sponsoring broker. Show 'CHN pending' status so users know why they can't trade yet. | G3: Critical | H3: Launch (Nov 2026) | I3: Approve
A4: T003 | B4: Onboarding & KYC | C4: Suitability and risk questionnaire | D4: Captures experience, risk appetite and income band; flags products that don't fit. | E4: Schwab, Robinhood (options approval) | F4: SEC Rule 76 requires digital sub-brokers to issue client suitability notifications. | G4: Critical | H4: Launch (Nov 2026) | I4: Approve
A5: T004 | B5: Onboarding & KYC | C5: Link an existing CHN and import holdings | D5: A user who already owns Nigerian shares sees them in the app on day one. | E5: Schwab/IBKR account transfers (ACATS); rare in Nigeria | F5: Many Nigerians hold shares they forgot about through registrars or old brokers. This is the bridge from the dividend recovery base into brokerage. | G5: Difference maker | H5: Phase 2 (Feb 2027) | I5: Approve
A6: T005 | B6: Onboarding & KYC | C6: Next-of-kin and beneficiary nomination | D6: User names who inherits the account and holdings. | E6: Schwab transfer-on-death beneficiaries | F6: Unclaimed dividends exist because holders die or vanish without a named heir. Prompt for this at signup and every year. | G6: Difference maker | H6: Launch (Nov 2026) | I6: Approve
A7: T006 | B7: Onboarding & KYC | C7: Estate and deceased-holder transmission flow | D7: Executors upload probate or letters of administration and move shares to heirs. | E7: Schwab estate services | F7: Reuses the estate claims workflow Vendii already runs for dividends. | G7: Difference maker | H7: Phase 3 (Mar 2027) | I7: Approve
A8: T007 | B8: Onboarding & KYC | C8: Tiered KYC with limits | D8: Start small with BVN only; raise limits by adding NIN and address proof. | E8: Most Nigerian fintechs (CBN tiered KYC practice) | F8: Utility bill upload is where most signups die. Let people invest ₦5,000 before asking for it. | G8: Good | H8: Launch (Nov 2026) | I8: Approve
A9: T008 | B9: Onboarding & KYC | C9: Save-and-resume onboarding | D9: User can stop halfway and continue later, on any device. | E9: Most modern apps | F9: Network drops and data costs make interrupted signups common. | G9: Good | H9: Launch (Nov 2026) | I9: Approve
A10: T009 | B10: Onboarding & KYC | C10: Diaspora onboarding | D10: Nigerians abroad open accounts with BVN/NIN, passport and foreign address. | E10: Bamboo, Risevest diaspora users | F10: Large holder segment for inherited shares and estates. FX funding rules limit how they fund. | G10: Good | H10: Phase 2 (Feb 2027) | I10: Approve
A11: T010 | B11: Onboarding & KYC | C11: Joint, minor (custodial) and corporate accounts | D11: Accounts for couples, children and companies. | E11: Schwab custodial, Robinhood multiple accounts | F11: Parents saving for school fees want child accounts. Corporate needs CAC documents and signatory rules. | G11: Nice to have | H11: Backlog | I11: Later
A12: T011 | B12: Funding & cash | C12: Dedicated virtual account number per user | D12: User funds by bank transfer to their own account number. | E12: Bamboo, Risevest, PiggyVest | F12: NIP transfer is how Nigerians move money. Cards fail more and cost more. | G12: Critical | H12: Launch (Nov 2026) | I12: Approve
A13: T012 | B13: Funding & cash | C13: Withdrawals only to BVN-matched bank account | D13: Cash can only leave to an account in the user's own name. | E13: Robinhood (linked bank only) | F13: Main fraud control. Changing the payout account needs 2FA and a cooling period. | G13: Critical | H13: Launch (Nov 2026) | I13: Approve
... A120: T119 | B120: Back office & compliance | C120: Product analytics and funnel tracking | D120: Where users drop off in signup, funding and first trade. | E120: Standard | F120: Tells you which of these features to build next. | G120: Good | H120: Launch (Nov 2026) | I120: Approve

Sheet Lending app
A1: ID | B1: Module | C1: Feature | D1: What it does | E1: Who does it well | F1: Nigeria adaptation | G1: Tier | H1: Suggested release | I1: Your call | J1: Your notes
A2: L001 | B2: Eligibility & offer | C2: Instant eligibility check | D2: User links holdings and sees the maximum loan in seconds, before applying. | E2: Volt Money, Groww Credit | F2: Biggest single conversion lever. Show the number before asking for any documents. | G2: Critical | H2: Launch (Mar 2027) | I2: Approve
A3: L002 | B3: Eligibility & offer | C3: Eligible securities list with advance rate per stock | D3: Public list of accepted stocks and how much can be borrowed against each. | E3: Schwab Advance Rate Lookup | F3: Start with liquid NGX names. Bank shares were barred from margin trading under the 2010 rules but can still back ordinary bank loans (CBN clarification). | G3: Critical | H3: Launch (Mar 2027) | I3: Approve
A4: L003 | B4: Eligibility & offer | C4: Loan calculator | D4: Amount, rate, tenor and total repayable on one screen. | E4: Jio Credit, Volt Money | F4: Show interest in naira, not just a percentage. | G4: Critical | H4: Launch (Mar 2027) | I4: Approve
A5: L004 | B5: Eligibility & offer | C5: Conservative valuation shown to the user | D5: Collateral valued at the lower of a recent average price and today's price. | E5: Global IME Bank, Nepal (lower of 180-day average or market) | F5: Protects against pumped thin NGX stocks and explains why the offer is lower than the portfolio value. | G5: Good | H5: Launch (Mar 2027) | I5: Approve
A6: L005 | B6: Eligibility & offer | C6: Soft pre-qualification | D6: Indicative offer without a hard credit bureau enquiry. | E6: Many digital lenders | F6: Lets users explore without fear of hurting their credit file. | G6: Good | H6: Launch (Mar 2027) | I6: Approve
A7: L006 | B7: Collateral | C7: Electronic lien with investor OTP consent | D7: Lien placed on chosen shares in favour of the lender, approved by the user with an OTP. | E7: India CDSL/NSDL pledge flow | F7: CSCS lien. Retail lien fees are set to be halved (reported Aug 2026). | G7: Critical | H7: Launch (Mar 2027) | I7: Approve
A8: L007 | B8: Collateral | C8: Check shares are not already pledged | D8: Confirms no existing lien before accepting collateral. | E8: Standard collateral checks | F8: Double-pledging is the main fraud risk. | G8: Critical | H8: Launch (Mar 2027) | I8: Approve
A9: L008 | B9: Collateral | C9: Concentration limits | D9: Caps how much of a loan can rest on one stock. | E9: Schwab, IBKR risk rules | F9: One NGX stock can gap down on a single announcement. | G9: Critical | H9: Launch (Mar 2027) | I9: Approve
A10: L009 | B10: Collateral | C10: Thin-liquidity haircuts | D10: Lower advance rates for stocks that trade little. | E10: IBKR concentration and liquidity haircuts | F10: A stock you can't sell in a margin call is not real collateral. | G10: Critical | H10: Launch (Mar 2027) | I10: Approve
A11: L010 | B11: Collateral | C11: Pledge shares held with any broker | D11: Borrow against NGX shares wherever they sit, not only at Vendii. | E11: Volt Money SDK model; locally VBank x Anchoria only serves Anchoria clients | F11: The open gap from the five-market research. Depends on CSCS lien mechanics across brokers (not verified; confirm with CSCS and Trust Bank). | G11: Difference maker | H11: Launch (Mar 2027) | I11: Approve
A12: L011 | B12: Collateral | C12: Pledge shares still in certificate or registrar form | D12: Help users dematerialise old holdings into CSCS so they can be pledged. | E12: None found | F12: Ties straight to Vendii's recovery base. Many old holdings are not yet in CSCS. | G12: Difference maker | H12: Phase 3 (Jul 2027) | I12: Approve
A13: L012 | B13: Collateral | C13: Partial pledge | D13: User picks which stocks and how many units to pledge. | E13: Groww Credit (flexible pledge) | F13: People want to keep some holdings free to sell. | G13: Good | H13: Launch (Mar 2027) | I13: Approve
... A67: L066 | B67: Scope extensions | C67: Spending categories and budgeting | D67: Tag what the loan was used for and track spending. | E67: Neobanks | F67: Not why anyone takes a share-backed loan. | G67: Nah, just there | H67: Skip | I67: Later

Sheet Design principles
A1: Applies to | B1: Principle | C1: What it means | D1: Example in Vendii
A2: Both | B2: Show the money before the button | C2: Every confirm screen shows what the user pays, every fee, and what they end up with. | D2: Order ticket shows ₦100,000 = 1,234 units + ₦1,850 in charges + ₦150 change. Loan offer shows total repayable in naira.
A3: Both | B3: Status over silence | C3: Every order, claim and loan shows where it is and what happens next. | D3: 'Sent to broker 10:42. Exchange opens 10:00 tomorrow.'
A4: Both | B4: Plain words, tap to explain | C4: Use everyday language and let users tap any term for a two-line definition. | D4: 'Qualification date' links to: own the shares before this date to get the dividend.
A5: Both | B5: Android-first, low data, low-end phones | C5: Design and test on a mid-range Android on 3G before anything else. | D5: Cache prices, compress images, keep the app small.
A6: Both | B6: Friction only where it protects | C6: Add steps for withdrawals, payout changes, loan signing. Remove them everywhere else. | D6: No PIN to view portfolio; PIN plus 2FA to change bank account.
A7: Both | B7: One main action per screen | C7: Each screen has one obvious next step. | D7: Stock page: Buy is primary, Sell secondary, everything else below the fold.
A8: Both | B8: Proof of custody, always visible | C8: Show that shares sit in the user's name at CSCS and who the licensed partners are. | D8: Settings > 'Where my shares are held' with CHN and sponsoring broker.
A9: Both | B9: Human escape hatch everywhere | C9: Every screen has a route to a person. | D9: 'Talk to us' in the header of order, claim and loan screens.
A10: Both | B10: Alerts say what to do, not just what happened | C10: Every notification carries the next action. | D10: 'Your loan health is amber. Add ₦45,000 or pledge more shares by Friday 2pm.'
A11: Both | B11: Interrupted sessions are normal | C11: Save progress on every step and resume on any device. | D11: Half-finished signup or loan application reopens where the user stopped.
A12: Both | B12: Naira formatting done right | C12: ₦ sign, thousands separators, kobo only where it matters, consistent everywhere. | D12: ₦1,250,000 not 1250000 NGN.
... A17: Lending | B17: No surprise sales | C17: Every forced sale is preceded by warnings and a visible countdown. | D17: Three alerts across channels, then a countdown on the home screen.

Sheet Sources
A1: Ref | B1: Source | C1: Link
A2: S1 | B2: Nairametrics, Top 10 investment apps in Nigeria as of May 2026 (Jun 2026) | C2: https://nairametrics.com/2026/06/02/top-10-investment-apps-in-in-nigeria-as-of-may-2026/
A3: S2 | B3: TechCabal, Apps Nigerians use to trade on the Nigerian stock exchange (Jul 2025) | C3: https://techcabal.com/2025/07/04/stock-investing-apps-nigerians-are-using-to-trade-in-2025/
A4: S3 | B4: TheCondia, Seven apps Nigerians use to invest in local stocks (2025) | C4: https://thecondia.com/best-apps-nigeria-stock-trading/
A5: S4 | B5: Daba Finance, Nigeria hikes capital requirements for capital market operators (Jan 2026) | C5: https://dabafinance.com/fr/nouvelles/nigeria-sec-revised-minimum-capital-rules
A6: S5 | B6: SEC Nigeria, SEC Rules for FinTechs (Rule 67 sub-brokers, Rule 76 digital sub-broker governance) | C6: https://www.sec.gov.ng/our-mandate/regulation/rules-and-regulations/sec-rules-for-fintechs/
A7: S6 | B7: Business Post, September 2026 FGN Savings Bond sales (Sep 2026) | C7: https://businesspost.ng/?p=212097
A8: S7 | B8: DMO public notice introducing the FGN Savings Bond (minimums by instrument) | C8: https://doclib.ngxgroup.com/products-site/bonds-site/Documents/Public%20Notice%20on%20the%20FGN%20Savings%20Bond.pdf
A9: S8 | B9: Nairametrics, CSCS to slash retail lien fees, scrap family transfer charges (Aug 2026) | C9: https://nairametrics.com/2026/08/26/breaking-cscs-to-slash-retail-lien-fees-scrap-family-transfer-charges-in-fresh-pricing-review/
A10: S9 | B10: How We Made It In Africa, New margin trading rules for Nigeria (FSRCC, 2010) | C10: https://www.howwemadeitinafrica.com/new-margin-trading-rules-for-nigeria/
A11: S10 | B11: Vanguard, CBN did not ban bank shares as loan collateral | C11: https://www.vanguardngr.com/?p=68407
A12: S11 | B12: TechCabal, VBank x Anchoria unveil shares-backed loan (Oct 2025) | C12: https://techcabal.com/2025/10/03/vbank-x-anchoria-unveil-shares-backed-loan-borrow-without-selling-your-stocks/
... A21: S20 | B21: SEC Nigeria, How margin loans work (investor education) | C21: https://sec.gov.ng/our-mandate/development/investor-education/investment-basics/how-margin-loans-work/
